GateMate FPGA Sim Rehber Turkce/src/fullAdder/fullAdder.v
`timescale 1ns / 1ps

module full_adder (

input  a,

input  b,

input  c_in,

output wire sum,

output wire carry_out

);

// Assign sum using XOR for efficient bitwise addition

assign sum = a ^ b ^ c_in;

// Assign carry based on two-bit product terms for clarity

assign carry_out = (a & b) | (a & c_in) | (c_in & b);

endmodule

src/fullAdder/fullAdderTB.v
`timescale 1ns / 1ps

module tb_full_adder;

// Declare testbench signals
reg a, b, c_in;
wire sum, carry_out;

// Instantiate the full adder module
full_adder dut (
    .a(a),
    .b(b),
    .c_in(c_in),
    .sum(sum),
    .carry_out(carry_out)
);

// Dumpfile and dumpvars for waveform generation
initial begin
    $dumpfile("fullAdderTB.vcd"); // Specify dump file name
    $dumpvars(0, tb_full_adder); // Dump all signals in the testbench
end

// Apply test stimulus
initial begin
    $display("Testing Full Adder");

    // Print header for the test cases
    $display("a   b   c_in | sum carry_out");
    $display("--------------------------");

    // Use $monitor to continuously display changes
    $monitor("%b   %b   %b    | %b   %b", a, b, c_in, sum, carry_out);

    // Apply all 8 test cases for a full adder
    a = 0; b = 0; c_in = 0; #10;
    a = 0; b = 0; c_in = 1; #10;
    a = 0; b = 1; c_in = 0; #10;
    a = 0; b = 1; c_in = 1; #10;
    a = 1; b = 0; c_in = 0; #10;
    a = 1; b = 0; c_in = 1; #10;
    a = 1; b = 1; c_in = 0; #10;
    a = 1; b = 1; c_in = 1; #10;

    #20; // Wait a little extra time to see the last result
    $finish;
end

endmodule

// You would need to include the full_adder module definition here or in a separate file.
/*
module full_adder(
    input a,
    input b,
    input c_in,
    output sum,
    output carry_out
);
    assign sum = a ^ b ^ c_in;
    assign carry_out = (a & b) | (b & c_in) | (a & c_in);
endmodule
*/

GateMate FPGA Sim Rehber Turkce/src/fullAdder/fullAdderTB.vcd
$date
	Wed Sep 03 13:33:16 2025
$end
$version
	Icarus Verilog
$end
$timescale
	1ps
$end
$scope module tb_full_adder $end
$var wire 1 ! sum $end
$var wire 1 " carry_out $end
$var reg 1 # a $end
$var reg 1 $ b $end
$var reg 1 % c_in $end
$scope module dut $end
$var wire 1 # a $end
$var wire 1 $ b $end
$var wire 1 % c_in $end
$var wire 1 " carry_out $end
$var wire 1 ! sum $end
$upscope $end
$upscope $end
$enddefinitions $end
$comment Show the parameter values. $end
$dumpall
$end
#0
$dumpvars
0%
0$
0#
0"
0!
$end
#10000
1!
1%
#20000
0%
1$
#30000
1"
0!
1%
#40000
0"
1!
0%
0$
1#
#50000
1"
0!
1%
#60000
0%
1$
#70000
1!
1%
